opentip/__init__.py
opentip/__main__.py
opentip/check_iocs.py
opentip/client.py
opentip/crontab.py
opentip/linux.py
opentip-1.2.dist-info/CLA.md
opentip-1.2.dist-info/License.txt
opentip-1.2.dist-info/METADATA
opentip-1.2.dist-info/WHEEL
opentip-1.2.dist-info/entry_points.txt
opentip-1.2.dist-info/legal_notices.txt
opentip-1.2.dist-info/top_level.txt
opentip-1.2.dist-info/RECORD
