Metadata-Version: 2.1
Name: opentip
Version: 1.2
Summary: Tools and Python API for accessing Kaspersky OpenTIP
Home-page: https://github.com/KasperskyLab/OpenTIP-scanner
Author: Kaspersky Lab
Author-email: igosha@kaspersky.com
Project-URL: Bug Tracker, https://github.com/KasperskyLab/OpenTIP-scanner/issues
Classifier: Programming Language :: Python :: 3
Classifier: License :: OSI Approved :: MIT License
Classifier: Operating System :: OS Independent
Requires-Python: >=3.8
License-File: License.txt
License-File: legal_notices.txt
License-File: CLA.md
